gts_engine_client/__init__.py
gts_engine_client/api.py
gts_engine_client-0.1.6.dist-info/LICENSE
gts_engine_client-0.1.6.dist-info/METADATA
gts_engine_client-0.1.6.dist-info/WHEEL
gts_engine_client-0.1.6.dist-info/top_level.txt
gts_engine_client-0.1.6.dist-info/RECORD
