Metadata-Version: 2.1
Name: gts-engine-client
Version: 0.1.6
Summary: gts_engine_client
Home-page: https://github.com/IDEA-CCNL/GTS-Engine-Client
Author: pankunhao
Author-email: pankunhao@gmail.com
License: MIT Licence
Platform: any
Classifier: Programming Language :: Python :: 3
Classifier: License :: OSI Approved :: MIT License
Classifier: Operating System :: OS Independent
License-File: LICENSE
Requires-Dist: requests (>=2.27)
